AUTHORS.txt
CHANGES.md
MANIFEST.in
README.md
VERSION
ez_setup.py
requirements.txt
setup.py
tox.ini
django_piston3.egg-info/PKG-INFO
django_piston3.egg-info/SOURCES.txt
django_piston3.egg-info/dependency_links.txt
django_piston3.egg-info/not-zip-safe
django_piston3.egg-info/requires.txt
django_piston3.egg-info/top_level.txt
examples/blogserver/README.txt
examples/blogserver/__init__.py
examples/blogserver/manage.py
examples/blogserver/settings.py
examples/blogserver/urls.py
examples/blogserver/api/__init__.py
examples/blogserver/api/handlers.py
examples/blogserver/api/urls.py
examples/blogserver/blog/__init__.py
examples/blogserver/blog/models.py
examples/blogserver/blog/urls.py
examples/blogserver/blog/views.py
examples/blogserver/fixtures/initial_data.xml
examples/blogserver/templates/posts.html
examples/blogserver/templates/test_js.html
piston/__init__.py
piston/admin.py
piston/authentication.py
piston/decorator.py
piston/doc.py
piston/emitters.py
piston/forms.py
piston/handler.py
piston/handlers_doc.py
piston/managers.py
piston/middleware.py
piston/models.py
piston/oauth.py
piston/resource.py
piston/signals.py
piston/store.py
piston/test.py
piston/tests.py
piston/utils.py
piston/validate_jsonp.py
piston/fixtures/models.json
piston/fixtures/oauth.json
piston/templates/documentation.html
piston/templates/piston/authorize_token.html
piston3/__init__.py
tests/bootstrap.py
tests/buildout.cfg
tests/test_project/__init__.py
tests/test_project/settings.py
tests/test_project/urls.py
tests/test_project/apps/__init__.py
tests/test_project/apps/testapp/__init__.py
tests/test_project/apps/testapp/forms.py
tests/test_project/apps/testapp/handlers.py
tests/test_project/apps/testapp/models.py
tests/test_project/apps/testapp/signals.py
tests/test_project/apps/testapp/tests.py
tests/test_project/apps/testapp/urls.py
tests/test_project/templates/404.html
tests/test_project/templates/500.html
tests/test_project/templates/admin/login.html