Metadata-Version: 1.1
Name: django-piston3
Version: 0.3rc2
Summary: Piston for Python 3.3+ and Django 1.6+ - Compatible with Python 2.7
Home-page: https://bitbucket.org/userzimmermann/django-piston3
Author: Stefan Zimmermann
Author-email: zimmermann.code@gmail.com
License: BSD
Download-URL: https://pypi.python.org/pypi/django-piston3
Keywords: django,piston3,piston,web,framework,api,rest,python3
Platform: UNKNOWN
Classifier: Development Status :: 4 - Beta
Classifier: Framework :: Django
Classifier: Intended Audience :: Developers
Classifier: License :: OSI Approved :: BSD License
Classifier: Operating System :: OS Independent
Classifier: Programming Language :: Python
Classifier: Programming Language :: Python :: 3
Classifier: Topic :: Internet :: WWW/HTTP
